privex/__init__.py
privex/iota/__init__.py
privex/iota/__main__.py
privex/iota/client.py
privex/iota/neighbors.py
privex/iota/objects.py
privex/iota/settings.py
privex/iota/status.py
privex_iota-0.8.0.data/scripts/iota-status
privex_iota-0.8.0.dist-info/LICENSE
privex_iota-0.8.0.dist-info/METADATA
privex_iota-0.8.0.dist-info/WHEEL
privex_iota-0.8.0.dist-info/top_level.txt
privex_iota-0.8.0.dist-info/RECORD
