Metadata-Version: 2.1
Name: privex-iota
Version: 0.8.0
Summary: Privex's Random IOTA Tools
Home-page: https://github.com/Privex/iota-tools
Author: Chris (Someguy123) @ Privex
Author-email: chris@privex.io
License: MIT
Platform: UNKNOWN
Classifier: Programming Language :: Python :: 3
Classifier: Programming Language :: Python :: 3.7
Classifier: Programming Language :: Python :: 3.8
Classifier: License :: OSI Approved :: MIT License
Classifier: Operating System :: POSIX :: Linux
Requires-Dist: privex-helpers (>=2.13.0)
Requires-Dist: pytz
Requires-Dist: colorama
Requires-Dist: PyOTA
Requires-Dist: requests
